vyked_orm/__init__.py
vyked_orm/constants.py
vyked_orm/data_types.py
vyked_orm/exceptions.py
vyked_orm/generic_manager.py
vyked_orm/generic_service.py
vyked_orm/generic_store.py
vyked_orm/generic_validation.py
vyked_orm/utils.py
vyked_orm-1.0.0.dist-info/DESCRIPTION.rst
vyked_orm-1.0.0.dist-info/METADATA
vyked_orm-1.0.0.dist-info/RECORD
vyked_orm-1.0.0.dist-info/WHEEL
vyked_orm-1.0.0.dist-info/metadata.json
vyked_orm-1.0.0.dist-info/top_level.txt
