Metadata-Version: 2.0
Name: vyked-orm
Version: 1.0.0
Summary: It create basic tcp http apis
Home-page: UNKNOWN
Author: Om Jangir
Author-email: omjangir2006@gmail.com
License: UNKNOWN
Platform: UNKNOWN
Requires-Dist: again
Requires-Dist: aiohttp
Requires-Dist: cauldron
Requires-Dist: vyked
